brio/__init__.py
brio/__main__.py
brio/application.py
brio/server.py
brio/version.py
brio/resources/brio.ini
brio/resources/brio.service
trimarlib_brio-0.1.0rc2.dist-info/METADATA
trimarlib_brio-0.1.0rc2.dist-info/RECORD
trimarlib_brio-0.1.0rc2.dist-info/WHEEL
trimarlib_brio-0.1.0rc2.dist-info/entry_points.txt
trimarlib_brio-0.1.0rc2.dist-info/top_level.txt
