Metadata-Version: 2.1
Name: trimarlib-brio
Version: 0.1.0rc2
Summary: Basic Remote IO Application
Home-page: https://dsl2.trimar.org/pythons-ll/brio
Author: TRIMAR Developer
Author-email: developer@trimar.com.pl
License: UNKNOWN
Platform: UNKNOWN
Classifier: Development Status :: 4 - Beta
Classifier: Environment :: Console
Classifier: License :: OSI Approved :: MIT License
Classifier: Natural Language :: English
Classifier: Operating System :: OS Independent
Classifier: Programming Language :: Python :: 3
Classifier: Topic :: Software Development :: Embedded Systems
Requires-Dist: trimarlib-sysfsgpio
Requires-Dist: trimarlib-newland
Requires-Dist: json-rpc
